JFlink
