Metadata-Version: 1.1
Name: JFlink
Version: 0.1.1
Summary: A collection of tools to improve workflow between JMCT and FISPACT
Home-page: https://github.com/starmode/JFlink
Author: UNKNOWN
Author-email: UNKNOWN
License: MIT License
Platform: any
Classifier: Development Status :: 3 - Alpha
Classifier: Environment :: Console
Classifier: Intended Audience :: Science/Research
Classifier: License :: OSI Approved :: MIT License
Classifier: Topic :: Scientific/Engineering
